CHANGES.txt
CONTRIBUTORS.txt
README.txt
bootstrap.py
buildout.cfg
setup.py
collective/__init__.py
collective.recipe.updateplone.egg-info/PKG-INFO
collective.recipe.updateplone.egg-info/SOURCES.txt
collective.recipe.updateplone.egg-info/dependency_links.txt
collective.recipe.updateplone.egg-info/entry_points.txt
collective.recipe.updateplone.egg-info/namespace_packages.txt
collective.recipe.updateplone.egg-info/not-zip-safe
collective.recipe.updateplone.egg-info/requires.txt
collective.recipe.updateplone.egg-info/top_level.txt
collective/recipe/__init__.py
collective/recipe/updateplone/README.txt
collective/recipe/updateplone/__init__.py
collective/recipe/updateplone/ploneupdater.py
collective/recipe/updateplone/script.py_tmpl
collective/recipe/updateplone/tests/__init__.py
collective/recipe/updateplone/tests/test_docs.py