Metadata-Version: 1.0
Name: collective.recipe.updateplone
Version: 0.3
Summary: A buildout recipe to update plone sites
Home-page: http://dev.plone.org/collective/browser/buildout/collective.recipe.updateplone
Author: Mustapha Benali, Anton Stonor
Author-email: mustapha@headnet.dk
License: ZPL
Keywords: buildout recipe update plone
Platform: UNKNOWN
Classifier: Framework :: Buildout
Classifier: Intended Audience :: Developers
Classifier: Topic :: Software Development :: Build Tools
Classifier: Topic :: Software Development :: Libraries :: Python Modules
Classifier: License :: OSI Approved :: Zope Public License
